main.py
primer_indel.py
bin/fq2vcf.py
bin/primerdesign_vcf.py
bin/vcf2del.py
primervcf/__init__.py
primervcf/map2vcf.py
primervcf/primer_indel.py
primervcf/utils.py
primervcf/vcfparser.py
primervcf-0.1.5.data/scripts/fq2vcf.py
primervcf-0.1.5.data/scripts/primerdesign_vcf.py
primervcf-0.1.5.data/scripts/vcf2del.py
primervcf-0.1.5.dist-info/METADATA
primervcf-0.1.5.dist-info/WHEEL
primervcf-0.1.5.dist-info/top_level.txt
primervcf-0.1.5.dist-info/RECORD
