Metadata-Version: 2.1
Name: primervcf
Version: 0.1.5
Summary: primer design for haplotype genotyping using indel information
Home-page: https://github.com/Runsheng/primervcf
Author: runsheng
Author-email: runsheng.lee@gmail.com
License: GPL-2
Requires-Dist: primer3-py (>=0.6.1)
Requires-Dist: biopython (>=1.78)
Requires-Dist: primerdiffer (>=0.1.4)
Requires-Dist: pyssw (>=0.1.4)
Requires-Dist: PyVCF3 (>=1.0.3)
